Metadata-Version: 1.0
Name: gaussian-and-binomial-pdf
Version: 0.1
Summary: Gaussian and Binomial distributions
Home-page: UNKNOWN
Author:  Aryan Gupta
Author-email: aryan.gupta.developer@gmail.com
License: UNKNOWN
Platform: UNKNOWN
